rgevolve/wet/jms/__init__.py
rgevolve/wet/jms/_version.py
rgevolve/wet/jms/data.h5
rgevolve_wet_jms-0.1.1.dist-info/licenses/LICENSE
rgevolve_wet_jms-0.1.1.dist-info/METADATA
rgevolve_wet_jms-0.1.1.dist-info/WHEEL
rgevolve_wet_jms-0.1.1.dist-info/top_level.txt
rgevolve_wet_jms-0.1.1.dist-info/RECORD
